llama_index/llms/rungpt/__init__.py
llama_index/llms/rungpt/base.py
llama_index_llms_rungpt-0.4.1.dist-info/METADATA
llama_index_llms_rungpt-0.4.1.dist-info/WHEEL
llama_index_llms_rungpt-0.4.1.dist-info/licenses/LICENSE
llama_index_llms_rungpt-0.4.1.dist-info/RECORD
